dingo/__init__.py
dingo/_version.py
dingo/asimov/__init__.py
dingo/asimov/asimov.py
dingo/asimov/dingo.ini
dingo/core/__init__.py
dingo/core/dataset.py
dingo/core/likelihood.py
dingo/core/multiprocessing.py
dingo/core/result.py
dingo/core/samplers.py
dingo/core/transforms.py
dingo/core/density/__init__.py
dingo/core/density/interpolation.py
dingo/core/density/nde_settings.py
dingo/core/density/unconditional_density_estimation.py
dingo/core/nn/__init__.py
dingo/core/nn/cfnets.py
dingo/core/nn/enets.py
dingo/core/nn/nsf.py
dingo/core/posterior_models/__init__.py
dingo/core/posterior_models/base_model.py
dingo/core/posterior_models/build_model.py
dingo/core/posterior_models/cflow_base.py
dingo/core/posterior_models/flow_matching.py
dingo/core/posterior_models/normalizing_flow.py
dingo/core/posterior_models/score_matching.py
dingo/core/utils/__init__.py
dingo/core/utils/backward_compatibility.py
dingo/core/utils/condor_utils.py
dingo/core/utils/gnpeutils.py
dingo/core/utils/logging_utils.py
dingo/core/utils/misc.py
dingo/core/utils/plotting.py
dingo/core/utils/pt_to_hdf5.py
dingo/core/utils/torchutils.py
dingo/core/utils/trainutils.py
dingo/gw/SVD.py
dingo/gw/__init__.py
dingo/gw/download_strain_data.py
dingo/gw/gwutils.py
dingo/gw/injection.py
dingo/gw/likelihood.py
dingo/gw/ls_cli.py
dingo/gw/prior.py
dingo/gw/result.py
dingo/gw/temporary_debug_utils.py
dingo/gw/conversion/__init__.py
dingo/gw/conversion/spin_conversion.py
dingo/gw/data/__init__.py
dingo/gw/data/data_download.py
dingo/gw/data/data_preparation.py
dingo/gw/data/event_dataset.py
dingo/gw/dataset/__init__.py
dingo/gw/dataset/evaluate_multibanded_domain.py
dingo/gw/dataset/generate_dataset.py
dingo/gw/dataset/generate_dataset_dag.py
dingo/gw/dataset/utils.py
dingo/gw/dataset/waveform_dataset.py
dingo/gw/domains/__init__.py
dingo/gw/domains/base.py
dingo/gw/domains/base_frequency_domain.py
dingo/gw/domains/build_domain.py
dingo/gw/domains/multibanded_frequency_domain.py
dingo/gw/domains/time_domain.py
dingo_gw-0.9.6.dist-info/licenses/AUTHORS.md
dingo_gw-0.9.6.dist-info/licenses/LICENSE
dingo_gw-0.9.6.dist-info/METADATA
dingo_gw-0.9.6.dist-info/WHEEL
dingo_gw-0.9.6.dist-info/entry_points.txt
dingo_gw-0.9.6.dist-info/top_level.txt
dingo_gw-0.9.6.dist-info/RECORD
