Metadata-Version: 2.4
Name: dingo-gw
Version: 0.9.6
Summary: Deep inference for gravitational-wave observations
Author-email: Maximilian Dax <maximilian.dax@tuebingen.mpg.de>, Stephen Green <Stephen.Green2@nottingham.ac.uk>
License: MIT
Project-URL: homepage, https://github.com/dingo-gw/dingo
Classifier: Programming Language :: Python :: 3
Classifier: Programming Language :: Python :: 3.10
Classifier: Programming Language :: Python :: 3.11
Classifier: License :: OSI Approved :: MIT License
Classifier: Operating System :: OS Independent
Requires-Python: <3.12,>=3.10
License-File: LICENSE
License-File: AUTHORS.md
Requires-Dist: astropy
Requires-Dist: bilby
Requires-Dist: bilby_pipe
Requires-Dist: configargparse
Requires-Dist: corner
Requires-Dist: glasflow
Requires-Dist: gwpy
Requires-Dist: h5py
Requires-Dist: lalsuite>=7.15
Requires-Dist: matplotlib
Requires-Dist: numpy
Requires-Dist: pandas
Requires-Dist: pycbc
Requires-Dist: pycondor
Requires-Dist: pyyaml
Requires-Dist: requests
Requires-Dist: scikit-learn
Requires-Dist: scipy
Requires-Dist: threadpoolctl
Requires-Dist: torch
Requires-Dist: torchdiffeq
Requires-Dist: torchvision
Requires-Dist: tqdm
Provides-Extra: dev
Requires-Dist: black; extra == "dev"
Requires-Dist: ipykernel; extra == "dev"
Requires-Dist: linkify-it-py; extra == "dev"
Requires-Dist: myst-nb; extra == "dev"
Requires-Dist: myst-parser; extra == "dev"
Requires-Dist: pandas-stubs>=2.3.3.251219; extra == "dev"
Requires-Dist: pytest; extra == "dev"
Requires-Dist: scipy-stubs>=1.15.3.0; extra == "dev"
Requires-Dist: sphinx; extra == "dev"
Requires-Dist: sphinx-math-dollar; extra == "dev"
Requires-Dist: sphinx-rtd-theme; extra == "dev"
Requires-Dist: sphinxcontrib-mermaid; extra == "dev"
Requires-Dist: sphinxcontrib-bibtex; extra == "dev"
Provides-Extra: wandb
Requires-Dist: wandb; extra == "wandb"
Provides-Extra: pyseobnr
Requires-Dist: pyseobnr; extra == "pyseobnr"
Dynamic: license-file
